T4ME-2.0.0.data/scripts/t4me
t4me/__init__.py
t4me/bandstructure.py
t4me/checktimings.py
t4me/constants.py
t4me/inputoutput.py
t4me/interface.py
t4me/lattice.py
t4me/lbtecoeff.py
t4me/lbteint.py
t4me/scattering.py
t4me/transport.py
t4me/utils.py
t4me/skw_interface/skw.cpp
t4me/skw_interface/skw_interface.hpp
t4me/spglib_interface/spglib.cpp
t4me/spglib_interface/spglib.pyx
t4me/spglib_interface/spglib_interface.cpp
t4me/spglib_interface/spglib_interface.hpp
t4me/tests/__init__.py
t4me/tests/fixtures.py
t4me/tests/test_symmetry.py
t4me/wildmagic_interface/wildmagic.cpp
t4me/wildmagic_interface/wildmagic.pyx
t4me/wildmagic_interface/wildmagic_interface.cpp
t4me/wildmagic_interface/wildmagic_interface.hpp
T4ME-2.0.0.dist-info/LICENSE.md
T4ME-2.0.0.dist-info/METADATA
T4ME-2.0.0.dist-info/WHEEL
T4ME-2.0.0.dist-info/top_level.txt
T4ME-2.0.0.dist-info/RECORD
