Metadata-Version: 2.1
Name: T4ME
Version: 2.0.0
Summary: T4ME - Transport for Materials.
Home-page: https://github.com/espenfl/t4me
Author: Espen Flage-Larsen
Author-email: espen.flage-larsen@sintef.no
License: BSD 3-clause license, see LICENSE.md file.
Keywords: vasp,materials,transport,boltzmann
Platform: UNKNOWN
Classifier: Development Status :: 4 - Beta
Classifier: Environment :: Plugins
Classifier: Intended Audience :: Science/Research
Classifier: License :: OSI Approved :: BSD License
Classifier: Programming Language :: Python :: 3.7
Classifier: Topic :: Scientific/Engineering :: Physics
Requires-Dist: numpy
Requires-Dist: PyYAML
Requires-Dist: spglib
Requires-Dist: scipy
Provides-Extra: dev
Requires-Dist: pre-commit (==1.18.3) ; extra == 'dev'
Requires-Dist: prospector (==1.1.7) ; extra == 'dev'
Requires-Dist: pylint (==2.3.1) ; extra == 'dev'
Requires-Dist: flake8 ; extra == 'dev'
Requires-Dist: yapf (==0.28.0) ; extra == 'dev'
Requires-Dist: coverage ; extra == 'dev'
Requires-Dist: pytest ; extra == 'dev'
Requires-Dist: pytest-cov ; extra == 'dev'
Requires-Dist: packaging ; extra == 'dev'
